TushuoShejimoshi/README.md
TushuoShejimoshi/__init__.py
TushuoShejimoshi/__main__.py
TushuoShejimoshi/file.epub
TushuoShejimoshi/index.html
TushuoShejimoshi/css/__init__.py
TushuoShejimoshi/css/annotations.css
TushuoShejimoshi/css/main.css
TushuoShejimoshi/css/normalize.css
TushuoShejimoshi/css/popup.css
TushuoShejimoshi/font/__init__.py
TushuoShejimoshi/font/fontello.eot
TushuoShejimoshi/font/fontello.svg
TushuoShejimoshi/font/fontello.ttf
TushuoShejimoshi/font/fontello.woff
TushuoShejimoshi/img/__init__.py
TushuoShejimoshi/img/annotator-glyph-sprite.png
TushuoShejimoshi/img/annotator-icon-sprite.png
TushuoShejimoshi/img/apple-touch-icon.png
TushuoShejimoshi/img/cancelfullscreen.png
TushuoShejimoshi/img/close.png
TushuoShejimoshi/img/fullscreen.png
TushuoShejimoshi/img/loader.gif
TushuoShejimoshi/img/menu-icon.png
TushuoShejimoshi/img/save.png
TushuoShejimoshi/img/saved.png
TushuoShejimoshi/img/settings-s.png
TushuoShejimoshi/img/settings.png
TushuoShejimoshi/img/star.png
TushuoShejimoshi/js/__init__.py
TushuoShejimoshi/js/epub.js
TushuoShejimoshi/js/epub.min.js
TushuoShejimoshi/js/epub.min.map
TushuoShejimoshi/js/hooks.min.js
TushuoShejimoshi/js/hooks.min.map
TushuoShejimoshi/js/reader.js
TushuoShejimoshi/js/reader.js.map
TushuoShejimoshi/js/reader.min.js
TushuoShejimoshi/js/reader.min.map
TushuoShejimoshi/js/hooks/__init__.py
TushuoShejimoshi/js/hooks/extensions/__init__.py
TushuoShejimoshi/js/hooks/extensions/highlight.js
TushuoShejimoshi/js/libs/__init__.py
TushuoShejimoshi/js/libs/jquery.min.js
TushuoShejimoshi/js/libs/localforage.min.js
TushuoShejimoshi/js/libs/screenfull.js
TushuoShejimoshi/js/libs/screenfull.min.js
TushuoShejimoshi/js/libs/zip.min.js
TushuoShejimoshi/js/plugins/__init__.py
TushuoShejimoshi/js/plugins/hypothesis.js
TushuoShejimoshi/js/plugins/search.js
tushuo_shejimoshi-2024.3.2.0.dist-info/METADATA
tushuo_shejimoshi-2024.3.2.0.dist-info/WHEEL
tushuo_shejimoshi-2024.3.2.0.dist-info/entry_points.txt
tushuo_shejimoshi-2024.3.2.0.dist-info/top_level.txt
tushuo_shejimoshi-2024.3.2.0.dist-info/RECORD
